<?xml version="1.0" encoding="UTF-8"?>
<antenna version="2.0">
	<name>Tarana_BN_5GHz_R1</name>
	<comment/>
	<frequency_min_MHz>0</frequency_min_MHz>
	<frequency_max_MHz>0</frequency_max_MHz>
	<electrical_downtilt_deg>0</electrical_downtilt_deg>
	<polarization>V</polarization>
	<main_radiation_pattern>
		<maximum_gain_dBi>17.65</maximum_gain_dBi>
		<horizontal_plane>
			<value_number>360</value_number>
			<gain angle="-180">-51.98</gain>
			<gain angle="-179">-51.98</gain>
			<gain angle="-178">-53.31</gain>
			<gain angle="-177">-56.65</gain>
			<gain angle="-176">-65.56</gain>
			<gain angle="-175">-64.7</gain>
			<gain angle="-174">-55.55</gain>
			<gain angle="-173">-51.56</gain>
			<gain angle="-172">-49.33</gain>
			<gain angle="-171">-48.02</gain>
			<gain angle="-170">-47.27</gain>
			<gain angle="-169">-46.87</gain>
			<gain angle="-168">-46.71</gain>
			<gain angle="-167">-46.84</gain>
			<gain angle="-166">-47.37</gain>
			<gain angle="-165">-48.51</gain>
			<gain angle="-164">-50.59</gain>
			<gain angle="-163">-54.25</gain>
			<gain angle="-162">-61.23</gain>
			<gain angle="-161">-64.93</gain>
			<gain angle="-160">-57.46</gain>
			<gain angle="-159">-54.23</gain>
			<gain angle="-158">-52.74</gain>
			<gain angle="-157">-51.57</gain>
			<gain angle="-156">-49.76</gain>
			<gain angle="-155">-47.43</gain>
			<gain angle="-154">-45.24</gain>
			<gain angle="-153">-43.55</gain>
			<gain angle="-152">-42.44</gain>
			<gain angle="-151">-41.86</gain>
			<gain angle="-150">-41.7</gain>
			<gain angle="-149">-41.82</gain>
			<gain angle="-148">-42</gain>
			<gain angle="-147">-42.11</gain>
			<gain angle="-146">-42.15</gain>
			<gain angle="-145">-42.32</gain>
			<gain angle="-144">-42.91</gain>
			<gain angle="-143">-44.22</gain>
			<gain angle="-142">-46.66</gain>
			<gain angle="-141">-51</gain>
			<gain angle="-140">-56.68</gain>
			<gain angle="-139">-52.18</gain>
			<gain angle="-138">-47.61</gain>
			<gain angle="-137">-45.06</gain>
			<gain angle="-136">-43.56</gain>
			<gain angle="-135">-42.52</gain>
			<gain angle="-134">-41.48</gain>
			<gain angle="-133">-40.29</gain>
			<gain angle="-132">-39.05</gain>
			<gain angle="-131">-37.99</gain>
			<gain angle="-130">-37.29</gain>
			<gain angle="-129">-37.02</gain>
			<gain angle="-128">-37.2</gain>
			<gain angle="-127">-37.77</gain>
			<gain angle="-126">-38.5</gain>
			<gain angle="-125">-38.95</gain>
			<gain angle="-124">-38.69</gain>
			<gain angle="-123">-37.83</gain>
			<gain angle="-122">-36.81</gain>
			<gain angle="-121">-35.98</gain>
			<gain angle="-120">-35.44</gain>
			<gain angle="-119">-35.17</gain>
			<gain angle="-118">-35.07</gain>
			<gain angle="-117">-34.97</gain>
			<gain angle="-116">-34.75</gain>
			<gain angle="-115">-34.34</gain>
			<gain angle="-114">-33.79</gain>
			<gain angle="-113">-33.2</gain>
			<gain angle="-112">-32.65</gain>
			<gain angle="-111">-32.2</gain>
			<gain angle="-110">-31.85</gain>
			<gain angle="-109">-31.58</gain>
			<gain angle="-108">-31.37</gain>
			<gain angle="-107">-31.17</gain>
			<gain angle="-106">-30.96</gain>
			<gain angle="-105">-30.71</gain>
			<gain angle="-104">-30.4</gain>
			<gain angle="-103">-30.03</gain>
			<gain angle="-102">-29.61</gain>
			<gain angle="-101">-29.13</gain>
			<gain angle="-100">-28.63</gain>
			<gain angle="-99">-28.11</gain>
			<gain angle="-98">-27.59</gain>
			<gain angle="-97">-27.08</gain>
			<gain angle="-96">-26.6</gain>
			<gain angle="-95">-26.14</gain>
			<gain angle="-94">-25.69</gain>
			<gain angle="-93">-25.25</gain>
			<gain angle="-92">-24.81</gain>
			<gain angle="-91">-24.35</gain>
			<gain angle="-90">-23.88</gain>
			<gain angle="-89">-23.37</gain>
			<gain angle="-88">-22.84</gain>
			<gain angle="-87">-22.29</gain>
			<gain angle="-86">-21.73</gain>
			<gain angle="-85">-21.18</gain>
			<gain angle="-84">-20.63</gain>
			<gain angle="-83">-20.09</gain>
			<gain angle="-82">-19.57</gain>
			<gain angle="-81">-19.07</gain>
			<gain angle="-80">-18.58</gain>
			<gain angle="-79">-18.1</gain>
			<gain angle="-78">-17.61</gain>
			<gain angle="-77">-17.12</gain>
			<gain angle="-76">-16.62</gain>
			<gain angle="-75">-16.1</gain>
			<gain angle="-74">-15.57</gain>
			<gain angle="-73">-15.03</gain>
			<gain angle="-72">-14.48</gain>
			<gain angle="-71">-13.93</gain>
			<gain angle="-70">-13.38</gain>
			<gain angle="-69">-12.84</gain>
			<gain angle="-68">-12.31</gain>
			<gain angle="-67">-11.79</gain>
			<gain angle="-66">-11.29</gain>
			<gain angle="-65">-10.81</gain>
			<gain angle="-64">-10.35</gain>
			<gain angle="-63">-9.91</gain>
			<gain angle="-62">-9.48</gain>
			<gain angle="-61">-9.09</gain>
			<gain angle="-60">-8.72</gain>
			<gain angle="-59">-8.38</gain>
			<gain angle="-58">-8.08</gain>
			<gain angle="-57">-7.81</gain>
			<gain angle="-56">-7.57</gain>
			<gain angle="-55">-7.38</gain>
			<gain angle="-54">-7.21</gain>
			<gain angle="-53">-7.07</gain>
			<gain angle="-52">-6.95</gain>
			<gain angle="-51">-6.84</gain>
			<gain angle="-50">-6.72</gain>
			<gain angle="-49">-6.6</gain>
			<gain angle="-48">-6.45</gain>
			<gain angle="-47">-6.29</gain>
			<gain angle="-46">-6.11</gain>
			<gain angle="-45">-5.91</gain>
			<gain angle="-44">-5.7</gain>
			<gain angle="-43">-5.49</gain>
			<gain angle="-42">-5.28</gain>
			<gain angle="-41">-5.09</gain>
			<gain angle="-40">-4.9</gain>
			<gain angle="-39">-4.74</gain>
			<gain angle="-38">-4.58</gain>
			<gain angle="-37">-4.43</gain>
			<gain angle="-36">-4.29</gain>
			<gain angle="-35">-4.15</gain>
			<gain angle="-34">-4.01</gain>
			<gain angle="-33">-3.86</gain>
			<gain angle="-32">-3.71</gain>
			<gain angle="-31">-3.56</gain>
			<gain angle="-30">-3.41</gain>
			<gain angle="-29">-3.27</gain>
			<gain angle="-28">-3.14</gain>
			<gain angle="-27">-3.02</gain>
			<gain angle="-26">-2.92</gain>
			<gain angle="-25">-2.82</gain>
			<gain angle="-24">-2.72</gain>
			<gain angle="-23">-2.63</gain>
			<gain angle="-22">-2.52</gain>
			<gain angle="-21">-2.41</gain>
			<gain angle="-20">-2.28</gain>
			<gain angle="-19">-2.15</gain>
			<gain angle="-18">-2</gain>
			<gain angle="-17">-1.87</gain>
			<gain angle="-16">-1.74</gain>
			<gain angle="-15">-1.62</gain>
			<gain angle="-14">-1.53</gain>
			<gain angle="-13">-1.45</gain>
			<gain angle="-12">-1.38</gain>
			<gain angle="-11">-1.33</gain>
			<gain angle="-10">-1.27</gain>
			<gain angle="-9">-1.19</gain>
			<gain angle="-8">-1.1</gain>
			<gain angle="-7">-0.98</gain>
			<gain angle="-6">-0.84</gain>
			<gain angle="-5">-0.69</gain>
			<gain angle="-4">-0.52</gain>
			<gain angle="-3">-0.36</gain>
			<gain angle="-2">-0.22</gain>
			<gain angle="-1">-0.1</gain>
			<gain angle="0">-0.0300001</gain>
			<gain angle="1">0</gain>
			<gain angle="2">-0.0199999</gain>
			<gain angle="3">-0.0800001</gain>
			<gain angle="4">-0.18</gain>
			<gain angle="5">-0.3</gain>
			<gain angle="6">-0.43</gain>
			<gain angle="7">-0.56</gain>
			<gain angle="8">-0.68</gain>
			<gain angle="9">-0.79</gain>
			<gain angle="10">-0.88</gain>
			<gain angle="11">-0.96</gain>
			<gain angle="12">-1.03</gain>
			<gain angle="13">-1.11</gain>
			<gain angle="14">-1.19</gain>
			<gain angle="15">-1.28</gain>
			<gain angle="16">-1.38</gain>
			<gain angle="17">-1.49</gain>
			<gain angle="18">-1.6</gain>
			<gain angle="19">-1.72</gain>
			<gain angle="20">-1.83</gain>
			<gain angle="21">-1.94</gain>
			<gain angle="22">-2.04</gain>
			<gain angle="23">-2.13</gain>
			<gain angle="24">-2.23</gain>
			<gain angle="25">-2.33</gain>
			<gain angle="26">-2.43</gain>
			<gain angle="27">-2.55</gain>
			<gain angle="28">-2.69</gain>
			<gain angle="29">-2.83</gain>
			<gain angle="30">-2.99</gain>
			<gain angle="31">-3.15</gain>
			<gain angle="32">-3.31</gain>
			<gain angle="33">-3.46</gain>
			<gain angle="34">-3.61</gain>
			<gain angle="35">-3.74</gain>
			<gain angle="36">-3.86</gain>
			<gain angle="37">-3.98</gain>
			<gain angle="38">-4.1</gain>
			<gain angle="39">-4.23</gain>
			<gain angle="40">-4.37</gain>
			<gain angle="41">-4.53</gain>
			<gain angle="42">-4.72</gain>
			<gain angle="43">-4.93</gain>
			<gain angle="44">-5.15</gain>
			<gain angle="45">-5.39</gain>
			<gain angle="46">-5.63</gain>
			<gain angle="47">-5.86</gain>
			<gain angle="48">-6.08</gain>
			<gain angle="49">-6.27</gain>
			<gain angle="50">-6.44</gain>
			<gain angle="51">-6.6</gain>
			<gain angle="52">-6.73</gain>
			<gain angle="53">-6.86</gain>
			<gain angle="54">-6.99</gain>
			<gain angle="55">-7.12</gain>
			<gain angle="56">-7.28</gain>
			<gain angle="57">-7.45</gain>
			<gain angle="58">-7.66</gain>
			<gain angle="59">-7.89</gain>
			<gain angle="60">-8.15</gain>
			<gain angle="61">-8.44</gain>
			<gain angle="62">-8.75</gain>
			<gain angle="63">-9.08</gain>
			<gain angle="64">-9.44</gain>
			<gain angle="65">-9.81</gain>
			<gain angle="66">-10.19</gain>
			<gain angle="67">-10.6</gain>
			<gain angle="68">-11.02</gain>
			<gain angle="69">-11.45</gain>
			<gain angle="70">-11.91</gain>
			<gain angle="71">-12.38</gain>
			<gain angle="72">-12.88</gain>
			<gain angle="73">-13.39</gain>
			<gain angle="74">-13.91</gain>
			<gain angle="75">-14.44</gain>
			<gain angle="76">-14.98</gain>
			<gain angle="77">-15.52</gain>
			<gain angle="78">-16.06</gain>
			<gain angle="79">-16.59</gain>
			<gain angle="80">-17.11</gain>
			<gain angle="81">-17.63</gain>
			<gain angle="82">-18.14</gain>
			<gain angle="83">-18.64</gain>
			<gain angle="84">-19.14</gain>
			<gain angle="85">-19.64</gain>
			<gain angle="86">-20.13</gain>
			<gain angle="87">-20.61</gain>
			<gain angle="88">-21.09</gain>
			<gain angle="89">-21.56</gain>
			<gain angle="90">-22.02</gain>
			<gain angle="91">-22.49</gain>
			<gain angle="92">-22.94</gain>
			<gain angle="93">-23.4</gain>
			<gain angle="94">-23.84</gain>
			<gain angle="95">-24.28</gain>
			<gain angle="96">-24.7</gain>
			<gain angle="97">-25.1</gain>
			<gain angle="98">-25.48</gain>
			<gain angle="99">-25.82</gain>
			<gain angle="100">-26.15</gain>
			<gain angle="101">-26.45</gain>
			<gain angle="102">-26.75</gain>
			<gain angle="103">-27.05</gain>
			<gain angle="104">-27.35</gain>
			<gain angle="105">-27.65</gain>
			<gain angle="106">-27.93</gain>
			<gain angle="107">-28.19</gain>
			<gain angle="108">-28.41</gain>
			<gain angle="109">-28.61</gain>
			<gain angle="110">-28.8</gain>
			<gain angle="111">-29.03</gain>
			<gain angle="112">-29.34</gain>
			<gain angle="113">-29.77</gain>
			<gain angle="114">-30.35</gain>
			<gain angle="115">-31.08</gain>
			<gain angle="116">-31.91</gain>
			<gain angle="117">-32.71</gain>
			<gain angle="118">-33.29</gain>
			<gain angle="119">-33.53</gain>
			<gain angle="120">-33.49</gain>
			<gain angle="121">-33.38</gain>
			<gain angle="122">-33.45</gain>
			<gain angle="123">-33.86</gain>
			<gain angle="124">-34.71</gain>
			<gain angle="125">-36.08</gain>
			<gain angle="126">-37.94</gain>
			<gain angle="127">-39.97</gain>
			<gain angle="128">-41.2</gain>
			<gain angle="129">-40.87</gain>
			<gain angle="130">-39.87</gain>
			<gain angle="131">-39.12</gain>
			<gain angle="132">-38.89</gain>
			<gain angle="133">-39.09</gain>
			<gain angle="134">-39.4</gain>
			<gain angle="135">-39.42</gain>
			<gain angle="136">-38.92</gain>
			<gain angle="137">-38.14</gain>
			<gain angle="138">-37.48</gain>
			<gain angle="139">-37.18</gain>
			<gain angle="140">-37.35</gain>
			<gain angle="141">-38.06</gain>
			<gain angle="142">-39.35</gain>
			<gain angle="143">-41.24</gain>
			<gain angle="144">-43.69</gain>
			<gain angle="145">-46.29</gain>
			<gain angle="146">-47.56</gain>
			<gain angle="147">-46.53</gain>
			<gain angle="148">-44.57</gain>
			<gain angle="149">-42.7</gain>
			<gain angle="150">-41.17</gain>
			<gain angle="151">-40.01</gain>
			<gain angle="152">-39.28</gain>
			<gain angle="153">-39.02</gain>
			<gain angle="154">-39.27</gain>
			<gain angle="155">-40.12</gain>
			<gain angle="156">-41.68</gain>
			<gain angle="157">-44.19</gain>
			<gain angle="158">-48.13</gain>
			<gain angle="159">-54.71</gain>
			<gain angle="160">-58.68</gain>
			<gain angle="161">-52.77</gain>
			<gain angle="162">-49.82</gain>
			<gain angle="163">-48.7</gain>
			<gain angle="164">-48.66</gain>
			<gain angle="165">-49.29</gain>
			<gain angle="166">-50.23</gain>
			<gain angle="167">-51.11</gain>
			<gain angle="168">-51.71</gain>
			<gain angle="169">-52.1</gain>
			<gain angle="170">-52.48</gain>
			<gain angle="171">-52.97</gain>
			<gain angle="172">-53.62</gain>
			<gain angle="173">-54.54</gain>
			<gain angle="174">-55.9</gain>
			<gain angle="175">-57.82</gain>
			<gain angle="176">-59.33</gain>
			<gain angle="177">-58.03</gain>
			<gain angle="178">-55.24</gain>
			<gain angle="179">-53.08</gain>
		</horizontal_plane>
		<vertical_plane>
			<value_number>360</value_number>
			<gain angle="-180">-52.35</gain>
			<gain angle="-179">-51.98</gain>
			<gain angle="-178">-52.04</gain>
			<gain angle="-177">-52.4</gain>
			<gain angle="-176">-52.79</gain>
			<gain angle="-175">-53.05</gain>
			<gain angle="-174">-53.31</gain>
			<gain angle="-173">-53.91</gain>
			<gain angle="-172">-55.09</gain>
			<gain angle="-171">-56.52</gain>
			<gain angle="-170">-56.45</gain>
			<gain angle="-169">-54.17</gain>
			<gain angle="-168">-51.64</gain>
			<gain angle="-167">-49.82</gain>
			<gain angle="-166">-48.79</gain>
			<gain angle="-165">-48.49</gain>
			<gain angle="-164">-48.82</gain>
			<gain angle="-163">-49.63</gain>
			<gain angle="-162">-50.64</gain>
			<gain angle="-161">-51.3</gain>
			<gain angle="-160">-51.22</gain>
			<gain angle="-159">-50.63</gain>
			<gain angle="-158">-49.99</gain>
			<gain angle="-157">-49.53</gain>
			<gain angle="-156">-49.27</gain>
			<gain angle="-155">-49.15</gain>
			<gain angle="-154">-49.17</gain>
			<gain angle="-153">-49.43</gain>
			<gain angle="-152">-50.05</gain>
			<gain angle="-151">-51.03</gain>
			<gain angle="-150">-51.71</gain>
			<gain angle="-149">-50.76</gain>
			<gain angle="-148">-48.32</gain>
			<gain angle="-147">-45.8</gain>
			<gain angle="-146">-43.8</gain>
			<gain angle="-145">-42.42</gain>
			<gain angle="-144">-41.63</gain>
			<gain angle="-143">-41.42</gain>
			<gain angle="-142">-41.79</gain>
			<gain angle="-141">-42.82</gain>
			<gain angle="-140">-44.64</gain>
			<gain angle="-139">-47.59</gain>
			<gain angle="-138">-52.41</gain>
			<gain angle="-137">-58.64</gain>
			<gain angle="-136">-54.39</gain>
			<gain angle="-135">-50.09</gain>
			<gain angle="-134">-47.91</gain>
			<gain angle="-133">-47.02</gain>
			<gain angle="-132">-47.1</gain>
			<gain angle="-131">-48</gain>
			<gain angle="-130">-49.52</gain>
			<gain angle="-129">-50.82</gain>
			<gain angle="-128">-50.29</gain>
			<gain angle="-127">-48.21</gain>
			<gain angle="-126">-46.12</gain>
			<gain angle="-125">-44.54</gain>
			<gain angle="-124">-43.51</gain>
			<gain angle="-123">-42.95</gain>
			<gain angle="-122">-42.77</gain>
			<gain angle="-121">-42.9</gain>
			<gain angle="-120">-43.27</gain>
			<gain angle="-119">-43.82</gain>
			<gain angle="-118">-44.51</gain>
			<gain angle="-117">-45.33</gain>
			<gain angle="-116">-46.26</gain>
			<gain angle="-115">-47.2</gain>
			<gain angle="-114">-47.86</gain>
			<gain angle="-113">-47.83</gain>
			<gain angle="-112">-47.06</gain>
			<gain angle="-111">-45.95</gain>
			<gain angle="-110">-44.9</gain>
			<gain angle="-109">-44.09</gain>
			<gain angle="-108">-43.57</gain>
			<gain angle="-107">-43.3</gain>
			<gain angle="-106">-43.24</gain>
			<gain angle="-105">-43.34</gain>
			<gain angle="-104">-43.56</gain>
			<gain angle="-103">-43.92</gain>
			<gain angle="-102">-44.45</gain>
			<gain angle="-101">-45.22</gain>
			<gain angle="-100">-46.26</gain>
			<gain angle="-99">-47.58</gain>
			<gain angle="-98">-49.14</gain>
			<gain angle="-97">-50.78</gain>
			<gain angle="-96">-52.32</gain>
			<gain angle="-95">-53.58</gain>
			<gain angle="-94">-54.44</gain>
			<gain angle="-93">-54.5</gain>
			<gain angle="-92">-53.36</gain>
			<gain angle="-91">-51.45</gain>
			<gain angle="-90">-49.5</gain>
			<gain angle="-89">-47.89</gain>
			<gain angle="-88">-46.7</gain>
			<gain angle="-87">-45.91</gain>
			<gain angle="-86">-45.42</gain>
			<gain angle="-85">-45.15</gain>
			<gain angle="-84">-44.99</gain>
			<gain angle="-83">-44.86</gain>
			<gain angle="-82">-44.7</gain>
			<gain angle="-81">-44.45</gain>
			<gain angle="-80">-44.03</gain>
			<gain angle="-79">-43.37</gain>
			<gain angle="-78">-42.45</gain>
			<gain angle="-77">-41.35</gain>
			<gain angle="-76">-40.2</gain>
			<gain angle="-75">-39.13</gain>
			<gain angle="-74">-38.18</gain>
			<gain angle="-73">-37.39</gain>
			<gain angle="-72">-36.72</gain>
			<gain angle="-71">-36.15</gain>
			<gain angle="-70">-35.62</gain>
			<gain angle="-69">-35.09</gain>
			<gain angle="-68">-34.52</gain>
			<gain angle="-67">-33.9</gain>
			<gain angle="-66">-33.21</gain>
			<gain angle="-65">-32.49</gain>
			<gain angle="-64">-31.77</gain>
			<gain angle="-63">-31.08</gain>
			<gain angle="-62">-30.45</gain>
			<gain angle="-61">-29.93</gain>
			<gain angle="-60">-29.52</gain>
			<gain angle="-59">-29.24</gain>
			<gain angle="-58">-29.09</gain>
			<gain angle="-57">-29.07</gain>
			<gain angle="-56">-29.17</gain>
			<gain angle="-55">-29.37</gain>
			<gain angle="-54">-29.68</gain>
			<gain angle="-53">-30.1</gain>
			<gain angle="-52">-30.67</gain>
			<gain angle="-51">-31.45</gain>
			<gain angle="-50">-32.53</gain>
			<gain angle="-49">-34.05</gain>
			<gain angle="-48">-36.23</gain>
			<gain angle="-47">-39.58</gain>
			<gain angle="-46">-45.58</gain>
			<gain angle="-45">-63.64</gain>
			<gain angle="-44">-45.62</gain>
			<gain angle="-43">-40.18</gain>
			<gain angle="-42">-37.36</gain>
			<gain angle="-41">-35.78</gain>
			<gain angle="-40">-35.06</gain>
			<gain angle="-39">-35.1</gain>
			<gain angle="-38">-36.04</gain>
			<gain angle="-37">-38.3</gain>
			<gain angle="-36">-43.45</gain>
			<gain angle="-35">-54.26</gain>
			<gain angle="-34">-40.11</gain>
			<gain angle="-33">-34.13</gain>
			<gain angle="-32">-30.54</gain>
			<gain angle="-31">-28.16</gain>
			<gain angle="-30">-26.59</gain>
			<gain angle="-29">-25.68</gain>
			<gain angle="-28">-25.32</gain>
			<gain angle="-27">-25.46</gain>
			<gain angle="-26">-25.92</gain>
			<gain angle="-25">-26.4</gain>
			<gain angle="-24">-26.39</gain>
			<gain angle="-23">-25.7</gain>
			<gain angle="-22">-24.72</gain>
			<gain angle="-21">-23.96</gain>
			<gain angle="-20">-23.76</gain>
			<gain angle="-19">-24.34</gain>
			<gain angle="-18">-26.01</gain>
			<gain angle="-17">-29.39</gain>
			<gain angle="-16">-35.81</gain>
			<gain angle="-15">-35.22</gain>
			<gain angle="-14">-29.35</gain>
			<gain angle="-13">-26.79</gain>
			<gain angle="-12">-26.76</gain>
			<gain angle="-11">-30.21</gain>
			<gain angle="-10">-35.04</gain>
			<gain angle="-9">-23.2</gain>
			<gain angle="-8">-16.58</gain>
			<gain angle="-7">-12.13</gain>
			<gain angle="-6">-8.82</gain>
			<gain angle="-5">-6.25</gain>
			<gain angle="-4">-4.25</gain>
			<gain angle="-3">-2.69</gain>
			<gain angle="-2">-1.52</gain>
			<gain angle="-1">-0.7</gain>
			<gain angle="0">-0.2</gain>
			<gain angle="1">0</gain>
			<gain angle="2">-0.1</gain>
			<gain angle="3">-0.51</gain>
			<gain angle="4">-1.24</gain>
			<gain angle="5">-2.31</gain>
			<gain angle="6">-3.76</gain>
			<gain angle="7">-5.65</gain>
			<gain angle="8">-8.1</gain>
			<gain angle="9">-11.3</gain>
			<gain angle="10">-15.67</gain>
			<gain angle="11">-22.43</gain>
			<gain angle="12">-41.94</gain>
			<gain angle="13">-28.33</gain>
			<gain angle="14">-23.86</gain>
			<gain angle="15">-22.64</gain>
			<gain angle="16">-22.69</gain>
			<gain angle="17">-23</gain>
			<gain angle="18">-22.69</gain>
			<gain angle="19">-21.67</gain>
			<gain angle="20">-20.56</gain>
			<gain angle="21">-19.82</gain>
			<gain angle="22">-19.62</gain>
			<gain angle="23">-20.01</gain>
			<gain angle="24">-21.01</gain>
			<gain angle="25">-22.64</gain>
			<gain angle="26">-24.81</gain>
			<gain angle="27">-26.97</gain>
			<gain angle="28">-27.86</gain>
			<gain angle="29">-27.17</gain>
			<gain angle="30">-26.2</gain>
			<gain angle="31">-25.74</gain>
			<gain angle="32">-26</gain>
			<gain angle="33">-27.06</gain>
			<gain angle="34">-29.08</gain>
			<gain angle="35">-32.45</gain>
			<gain angle="36">-38.45</gain>
			<gain angle="37">-50.04</gain>
			<gain angle="38">-40.15</gain>
			<gain angle="39">-35.74</gain>
			<gain angle="40">-34.07</gain>
			<gain angle="41">-33.9</gain>
			<gain angle="42">-34.85</gain>
			<gain angle="43">-36.58</gain>
			<gain angle="44">-37.7</gain>
			<gain angle="45">-36.31</gain>
			<gain angle="46">-33.78</gain>
			<gain angle="47">-31.67</gain>
			<gain angle="48">-30.23</gain>
			<gain angle="49">-29.4</gain>
			<gain angle="50">-29.11</gain>
			<gain angle="51">-29.3</gain>
			<gain angle="52">-29.96</gain>
			<gain angle="53">-31.08</gain>
			<gain angle="54">-32.71</gain>
			<gain angle="55">-34.96</gain>
			<gain angle="56">-38.08</gain>
			<gain angle="57">-42.68</gain>
			<gain angle="58">-51.15</gain>
			<gain angle="59">-54.36</gain>
			<gain angle="60">-45.75</gain>
			<gain angle="61">-42.01</gain>
			<gain angle="62">-39.9</gain>
			<gain angle="63">-38.61</gain>
			<gain angle="64">-37.85</gain>
			<gain angle="65">-37.46</gain>
			<gain angle="66">-37.39</gain>
			<gain angle="67">-37.6</gain>
			<gain angle="68">-38.07</gain>
			<gain angle="69">-38.81</gain>
			<gain angle="70">-39.81</gain>
			<gain angle="71">-41.1</gain>
			<gain angle="72">-42.64</gain>
			<gain angle="73">-44.34</gain>
			<gain angle="74">-45.8</gain>
			<gain angle="75">-46.38</gain>
			<gain angle="76">-45.87</gain>
			<gain angle="77">-44.78</gain>
			<gain angle="78">-43.65</gain>
			<gain angle="79">-42.69</gain>
			<gain angle="80">-41.92</gain>
			<gain angle="81">-41.32</gain>
			<gain angle="82">-40.9</gain>
			<gain angle="83">-40.66</gain>
			<gain angle="84">-40.63</gain>
			<gain angle="85">-40.87</gain>
			<gain angle="86">-41.42</gain>
			<gain angle="87">-42.32</gain>
			<gain angle="88">-43.61</gain>
			<gain angle="89">-45.24</gain>
			<gain angle="90">-46.98</gain>
			<gain angle="91">-48.14</gain>
			<gain angle="92">-47.85</gain>
			<gain angle="93">-46.42</gain>
			<gain angle="94">-44.75</gain>
			<gain angle="95">-43.28</gain>
			<gain angle="96">-42.16</gain>
			<gain angle="97">-41.43</gain>
			<gain angle="98">-41.13</gain>
			<gain angle="99">-41.29</gain>
			<gain angle="100">-41.99</gain>
			<gain angle="101">-43.3</gain>
			<gain angle="102">-45.29</gain>
			<gain angle="103">-47.7</gain>
			<gain angle="104">-48.99</gain>
			<gain angle="105">-47.65</gain>
			<gain angle="106">-45.51</gain>
			<gain angle="107">-43.91</gain>
			<gain angle="108">-43.02</gain>
			<gain angle="109">-42.79</gain>
			<gain angle="110">-43.2</gain>
			<gain angle="111">-44.26</gain>
			<gain angle="112">-46.12</gain>
			<gain angle="113">-49.17</gain>
			<gain angle="114">-54.62</gain>
			<gain angle="115">-65.61</gain>
			<gain angle="116">-55.11</gain>
			<gain angle="117">-49.63</gain>
			<gain angle="118">-46.71</gain>
			<gain angle="119">-45.06</gain>
			<gain angle="120">-44.26</gain>
			<gain angle="121">-44.13</gain>
			<gain angle="122">-44.54</gain>
			<gain angle="123">-45.31</gain>
			<gain angle="124">-46.14</gain>
			<gain angle="125">-46.68</gain>
			<gain angle="126">-46.82</gain>
			<gain angle="127">-46.93</gain>
			<gain angle="128">-47.52</gain>
			<gain angle="129">-49.01</gain>
			<gain angle="130">-51.78</gain>
			<gain angle="131">-54.95</gain>
			<gain angle="132">-53.12</gain>
			<gain angle="133">-49.34</gain>
			<gain angle="134">-46.92</gain>
			<gain angle="135">-45.85</gain>
			<gain angle="136">-46.01</gain>
			<gain angle="137">-47.57</gain>
			<gain angle="138">-51.27</gain>
			<gain angle="139">-59.04</gain>
			<gain angle="140">-54.16</gain>
			<gain angle="141">-47.94</gain>
			<gain angle="142">-44.7</gain>
			<gain angle="143">-42.97</gain>
			<gain angle="144">-42.25</gain>
			<gain angle="145">-42.32</gain>
			<gain angle="146">-43.09</gain>
			<gain angle="147">-44.46</gain>
			<gain angle="148">-46.33</gain>
			<gain angle="149">-48.57</gain>
			<gain angle="150">-51.09</gain>
			<gain angle="151">-54.35</gain>
			<gain angle="152">-59.79</gain>
			<gain angle="153">-60.56</gain>
			<gain angle="154">-53.12</gain>
			<gain angle="155">-48.63</gain>
			<gain angle="156">-45.91</gain>
			<gain angle="157">-44.38</gain>
			<gain angle="158">-43.8</gain>
			<gain angle="159">-44.12</gain>
			<gain angle="160">-45.46</gain>
			<gain angle="161">-48.13</gain>
			<gain angle="162">-53.1</gain>
			<gain angle="163">-60.93</gain>
			<gain angle="164">-54.64</gain>
			<gain angle="165">-50.07</gain>
			<gain angle="166">-48.03</gain>
			<gain angle="167">-47.45</gain>
			<gain angle="168">-47.99</gain>
			<gain angle="169">-49.49</gain>
			<gain angle="170">-51.65</gain>
			<gain angle="171">-53.34</gain>
			<gain angle="172">-53.14</gain>
			<gain angle="173">-52.01</gain>
			<gain angle="174">-51.33</gain>
			<gain angle="175">-51.42</gain>
			<gain angle="176">-52.14</gain>
			<gain angle="177">-53.06</gain>
			<gain angle="178">-53.43</gain>
			<gain angle="179">-53.01</gain>
		</vertical_plane>
	</main_radiation_pattern>
</antenna>

